[
  { "level": "N4", "nomor": 1, "pola": "〜たら", "arti_pola": "Kalau/jika sudah〜", "penjelasan": "Menyatakan syarat, ditempel pada bentuk ~ta suatu kata kerja/kata sifat.", "contoh_kalimat": "あめが ふったら、いえに います。", "contoh_arti": "Kalau hujan turun, saya akan tinggal di rumah." },
  { "level": "N4", "nomor": 2, "pola": "〜ば", "arti_pola": "Jika〜(bentuk bersyarat)", "penjelasan": "Bentuk bersyarat formal, dipakai untuk menyatakan syarat umum atau hipotesis.", "contoh_kalimat": "はやく おきれば、まにあいます。", "contoh_arti": "Jika bangun lebih awal, akan tepat waktu." },
  { "level": "N4", "nomor": 3, "pola": "〜ようになる", "arti_pola": "Menjadi bisa/terbiasa〜", "penjelasan": "Menyatakan perubahan kemampuan atau kebiasaan seiring waktu.", "contoh_kalimat": "かんじが よめるようになりました。", "contoh_arti": "Saya jadi bisa membaca kanji." },
  { "level": "N4", "nomor": 4, "pola": "〜そうです（様態）", "arti_pola": "Kelihatannya〜", "penjelasan": "Menyatakan kesan visual/dugaan berdasarkan penampilan, ditempel pada batang kata sifat.", "contoh_kalimat": "この ケーキは おいしそうです。", "contoh_arti": "Kue ini kelihatannya enak." },
  { "level": "N4", "nomor": 5, "pola": "〜かもしれません", "arti_pola": "Mungkin saja〜", "penjelasan": "Menyatakan kemungkinan dengan tingkat keyakinan rendah.", "contoh_kalimat": "あした ゆきが ふるかもしれません。", "contoh_arti": "Besok mungkin saja turun salju." },
  { "level": "N4", "nomor": 6, "pola": "〜てもいいです", "arti_pola": "Boleh〜", "penjelasan": "Menyatakan izin melakukan sesuatu, memakai bentuk ~te dari kata kerja.", "contoh_kalimat": "ここに すわってもいいです。", "contoh_arti": "Boleh duduk di sini." },
  { "level": "N4", "nomor": 7, "pola": "〜なければなりません", "arti_pola": "Harus〜", "penjelasan": "Menyatakan kewajiban, memakai bentuk negatif ~nai kata kerja lalu ditambah ければなりません.", "contoh_kalimat": "しゅくだいを しなければなりません。", "contoh_arti": "Saya harus mengerjakan PR." },
  { "level": "N4", "nomor": 8, "pola": "〜ておく", "arti_pola": "Melakukan〜lebih dulu (persiapan)", "penjelasan": "Menyatakan tindakan dilakukan sebagai persiapan untuk sesuatu yang akan terjadi.", "contoh_kalimat": "りょこうの まえに きっぷを かっておきます。", "contoh_arti": "Saya membeli tiket dulu sebelum perjalanan." },
  { "level": "N4", "nomor": 9, "pola": "〜てしまう", "arti_pola": "Terlanjur/selesai melakukan〜", "penjelasan": "Menyatakan sesuatu selesai sepenuhnya atau menyesalkan suatu tindakan.", "contoh_kalimat": "レポートを わすれてしまいました。", "contoh_arti": "Saya terlanjur lupa membawa laporan." },
  { "level": "N4", "nomor": 10, "pola": "〜あいだに", "arti_pola": "Selagi〜", "penjelasan": "Menyatakan sesuatu terjadi dalam rentang waktu tertentu.", "contoh_kalimat": "こどもが ねているあいだに、そうじします。", "contoh_arti": "Selagi anak tidur, saya bersih-bersih." },
  { "level": "N4", "nomor": 11, "pola": "〜について", "arti_pola": "Tentang〜", "penjelasan": "Menandai topik pembicaraan atau tulisan secara lebih spesifik daripada は.", "contoh_kalimat": "にほんの ぶんかについて はなします。", "contoh_arti": "Saya berbicara tentang budaya Jepang." },
  { "level": "N4", "nomor": 12, "pola": "〜のに", "arti_pola": "Padahal〜(kontras/kekecewaan)", "penjelasan": "Menghubungkan dua klausa yang bertentangan, sering mengandung nuansa kecewa atau heran.", "contoh_kalimat": "いっしょうけんめい べんきょうしたのに、しけんに おちました。", "contoh_arti": "Padahal sudah belajar sungguh-sungguh, tapi gagal ujian." }
]
